Metadata-Version: 1.1
Name: atomgen
Version: 0.1.9
Summary: Creates Apple Newsstand Atom Feed
Home-page: https://github.com/erasmose/atomgen
Author: Erasmose
Author-email: sep@zepworks.com
License: MIT
Download-URL: https://github.com/erasmose/atomgen/tarball/master
Platform: UNKNOWN
Classifier: Environment :: Web Environment
Classifier: Intended Audience :: Developers
Classifier: Operating System :: OS Independent
Classifier: Topic :: Software Development
Classifier: Programming Language :: Python
Classifier: Programming Language :: Python :: 2.7
Classifier: Programming Language :: Python :: 3.3
